django_teryt-0.3.0.dist-info/DESCRIPTION.rst
django_teryt-0.3.0.dist-info/METADATA
django_teryt-0.3.0.dist-info/RECORD
django_teryt-0.3.0.dist-info/WHEEL
django_teryt-0.3.0.dist-info/metadata.json
django_teryt-0.3.0.dist-info/top_level.txt
teryt/__init__.py
teryt/models.py
teryt/utils.py
teryt/integration_tests/__init__.py
teryt/integration_tests/test_management.py
teryt/management/__init__.py
teryt/management/commands/__init__.py
teryt/management/commands/teryt_parse.py
teryt/migrations/0001_initial.py
teryt/migrations/0002_add_aktywny.py
teryt/migrations/0003_update_aktywny.py
teryt/migrations/0004_set_aktywny_not_null.py
teryt/migrations/0005_rename_RodzajMiejsowosci.py
teryt/migrations/0006_add_JednostkaAdministracyjna_typ.py
teryt/migrations/__init__.py
teryt/south_migrations/0001_initial.py
teryt/south_migrations/0002_auto__add_field_miejscowosc_aktywny__add_field_ulica_aktywny__add_fiel.py
teryt/south_migrations/0003_ustaw_aktywny.py
teryt/south_migrations/0004_auto__chg_field_miejscowosc_aktywny__chg_field_ulica_aktywny__chg_fiel.py
teryt/south_migrations/0005_rename_RodzajMiejsowosci.py
teryt/south_migrations/0006_add_JednostkaAdministracyjna_typ.py
teryt/south_migrations/0007_update_JednostkaAdministracyjna_typ.py
teryt/south_migrations/0008_set_not_null_JednostkaAdministracyjna_typ.py
teryt/south_migrations/__init__.py
teryt/tests/__init__.py
teryt/tests/factories.py
teryt/tests/test_models.py
