Metadata-Version: 2.0
Name: django-teryt
Version: 0.3.0
Summary: TERYT database implementation for Django
Home-page: https://github.com/scibi/django-teryt
Author: Patryk Ściborek
Author-email: patryk@sciborek.com
License: MIT
Keywords: django-teryt
Platform: UNKNOWN
Classifier: Development Status :: 4 - Beta
Classifier: Framework :: Django
Classifier: Framework :: Django :: 1.6
Classifier: Framework :: Django :: 1.7
Classifier: Framework :: Django :: 1.8
Classifier: Framework :: Django :: 1.9
Classifier: Intended Audience :: Developers
Classifier: License :: OSI Approved :: BSD License
Classifier: Natural Language :: Polish
Classifier: Programming Language :: Python :: 2
Classifier: Programming Language :: Python :: 2.7
Classifier: Programming Language :: Python :: 3
Classifier: Programming Language :: Python :: 3.4
